README.md
setup.py
kraem/__init__.py
kraem/cli.py
kraem/compress.py
kraem/engine.py
kraem/gcs.py
kraem/statistics.py
kraem/utils.py
kraem.egg-info/PKG-INFO
kraem.egg-info/SOURCES.txt
kraem.egg-info/dependency_links.txt
kraem.egg-info/entry_points.txt
kraem.egg-info/requires.txt
kraem.egg-info/top_level.txt