Metadata-Version: 1.1
Name: kraem
Version: 0.0.3
Summary: Image compression and manipulation CLI with cloud storage upload
Home-page: https://github.com/bjarneo/kraem
Author: Bjarne Oeverli
Author-email: UNKNOWN
License: UNKNOWN
Keywords: image-processing images compression compress mozjpeg gcs gcp gcp-storage
Platform: UNKNOWN
Classifier: Intended Audience :: Developers
Classifier: Programming Language :: Python :: 3.4
Classifier: Programming Language :: Python :: 3.5
Classifier: Programming Language :: Python :: 3.6
Classifier: Programming Language :: Python
